britz/__init__.py
britz/__main__.py
britz/cli.py
britz-0.0.0.dist-info/entry_points.txt
britz-0.0.0.dist-info/COPYING
britz-0.0.0.dist-info/WHEEL
britz-0.0.0.dist-info/METADATA
britz-0.0.0.dist-info/RECORD
