Metadata-Version: 2.1
Name: britz
Version: 0.0.0
Summary: Easily review dependencies between SQL Transformations
Home-page: https://github.com/JimFawkes/britz
License: UNKNOWN
Author: Moritz Eilfort
Author-email: britz@jimfawkes.com
Requires-Python: >=3.8
Classifier: Intended Audience :: Developers
Classifier: Natural Language :: English
Classifier: License :: OSI Approved :: GNU General Public License v3 or later (GPLv3+)
Classifier: Programming Language :: Python :: 3.8
Classifier: Topic :: Software Development :: Libraries :: Python Modules
Requires-Dist: pglast==1.13
Requires-Dist: pytest==6.1.1 ; extra == "test"
Requires-Dist: pytest-cov ; extra == "test"
Provides-Extra: test
